{
  "main": {
    "id": "b6f26126a80d42ad",
    "type": "split",
    "children": [
      {
        "id": "4f79ad6afa2c1384",
        "type": "tabs",
        "children": [
          {
            "id": "c06f1333a9a758a6",
            "type": "leaf",
            "state": {
              "type": "markdown",
              "state": {
                "file": "Places/Astral Sea.md",
                "mode": "source",
                "source": false
              },
              "icon": "lucide-file",
              "title": "Astral Sea"
            }
          }
        ]
      }
    ],
    "direction": "vertical"
  },
  "left": {
    "id": "ba73290034bcdaa8",
    "type": "split",
    "children": [
      {
        "id": "ac6936e773289fdf",
        "type": "tabs",
        "children": [
          {
            "id": "cff70342460ff2f9",
            "type": "leaf",
            "state": {
              "type": "file-explorer",
              "state": {
                "sortOrder": "alphabetical",
                "autoReveal": false
              },
              "icon": "lucide-folder-closed",
              "title": "Files"
            }
          },
          {
            "id": "12d4908a6c73c831",
            "type": "leaf",
            "state": {
              "type": "search",
              "state": {
                "query": "seven",
                "matchingCase": false,
                "explainSearch": false,
                "collapseAll": false,
                "extraContext": false,
                "sortOrder": "alphabetical"
              },
              "icon": "lucide-search",
              "title": "Search"
            }
          },
          {
            "id": "3232133b80060415",
            "type": "leaf",
            "state": {
              "type": "bookmarks",
              "state": {},
              "icon": "lucide-bookmark",
              "title": "Bookmarks"
            }
          }
        ]
      }
    ],
    "direction": "horizontal",
    "width": 300
  },
  "right": {
    "id": "bef47bed338824f2",
    "type": "split",
    "children": [
      {
        "id": "fa5afc4a702fb01e",
        "type": "tabs",
        "children": [
          {
            "id": "3a5bd0778785649f",
            "type": "leaf",
            "state": {
              "type": "tag",
              "state": {
                "sortOrder": "frequency",
                "useHierarchy": false,
                "showSearch": false,
                "searchQuery": ""
              },
              "icon": "lucide-tags",
              "title": "Tags"
            }
          },
          {
            "id": "8743808c26d6355a",
            "type": "leaf",
            "state": {
              "type": "outline",
              "state": {
                "followCursor": false,
                "showSearch": false,
                "searchQuery": ""
              },
              "icon": "lucide-list",
              "title": "Outline"
            }
          },
          {
            "id": "1a3e7841446eb68f",
            "type": "leaf",
            "state": {
              "type": "git-view",
              "state": {},
              "icon": "git-pull-request",
              "title": "Source Control"
            }
          },
          {
            "id": "5bfb496eac7d795b",
            "type": "leaf",
            "state": {
              "type": "backlink",
              "state": {
                "file": "Sessions/Session 14 - His Name was Magic Johnson.md",
                "collapseAll": false,
                "extraContext": false,
                "sortOrder": "alphabetical",
                "showSearch": false,
                "searchQuery": "",
                "backlinkCollapsed": false,
                "unlinkedCollapsed": true
              },
              "icon": "links-coming-in",
              "title": "Backlinks for Session 14 - His Name was Magic Johnson"
            }
          },
          {
            "id": "9b7290c1dd25394b",
            "type": "leaf",
            "state": {
              "type": "outgoing-link",
              "state": {
                "linksCollapsed": false,
                "unlinkedCollapsed": true
              },
              "icon": "links-going-out",
              "title": "Outgoing links"
            }
          }
        ],
        "currentTab": 2
      }
    ],
    "direction": "horizontal",
    "width": 300
  },
  "left-ribbon": {
    "hiddenItems": {
      "bases:Create new base": false,
      "switcher:Open quick switcher": false,
      "graph:Open graph view": false,
      "canvas:Create new canvas": false,
      "daily-notes:Open today's daily note": false,
      "templates:Insert template": false,
      "command-palette:Open command palette": false,
      "obsidian-git:Open Git source control": false
    }
  },
  "active": "cff70342460ff2f9",
  "lastOpenFiles": [
    "Characters/Alustriel Silverhand.md",
    "Characters/Ambrose.md",
    "Characters/B.md",
    "Characters/Dusty.md",
    "Characters/Karsus.md",
    "Characters/L.S..md",
    "Characters/Lady Shar.md",
    "Characters/Mordenkainen.md",
    "Characters/Myrkul.md",
    "Characters/The Third.md",
    "Unsolved Ciphers/cipher work spreadsheet.md",
    "Unsolved Ciphers/silence.md",
    "Other Texts/The Last of the Dreamers.md",
    "Other Texts/Skate Logbook.md",
    "Other Texts/Ruby Poem.md",
    "Other Texts/Parable of Myrkul.md",
    "Other Texts/Nyxaris's Dream.md",
    "Other Texts/Letter to Dusty.md",
    "Other Texts/Legend Lores.md",
    "Other Texts/His Name Was Magic.md",
    "Other Texts/Greatness Born Or Made.md",
    "Decoded Ciphers/A_New_Vow.md",
    "fih/misc messages not entered before.md",
    "Decoded Ciphers/wonderfulidea.md",
    "B..md",
    "Sessions/Session 18 - Welcome to the Dream Kingdom Bitch.md",
    "Images/Pasted image 20250713125547.png",
    "Pasted image 20250713125547.png",
    "Pasted image 20250821181619.png",
    "Pasted image 20250713161155.png",
    "Pasted image 20250713161053.png",
    "Pasted image 20250713160843.png",
    "Pasted image 20250713160437.png",
    "Pasted image 20250713154512.png",
    "Pasted image 20250713154140.png",
    "Pasted image 20250713140831.png",
    "Images",
    "Untitled.base",
    "Untitled.canvas",
    "crazypheights",
    "Unsolved Ciphers",
    "fih",
    "Misc",
    "Characters",
    "Concepts and Esoterica",
    "Places",
    "Other Texts"
  ]
}